Metadata-Version: 1.0
Name: lsywywsdk
Version: 0.1.0
Summary: sdk for lsywywtools
Home-page: UNKNOWN
Author: zhoujianhua
Author-email: UNKNOWN
License: UNKNOWN
Platform: UNKNOWN
